MDTerp/__init__.py
MDTerp/base.py
MDTerp/final_analysis.py
MDTerp/init_analysis.py
MDTerp/neighborhood.py
MDTerp/utils.py
mdterp-1.4.0.dist-info/licenses/LICENSE
mdterp-1.4.0.dist-info/METADATA
mdterp-1.4.0.dist-info/WHEEL
mdterp-1.4.0.dist-info/entry_points.txt
mdterp-1.4.0.dist-info/top_level.txt
mdterp-1.4.0.dist-info/RECORD
