Metadata-Version: 2.4
Name: MDTerp
Version: 1.4.0
Summary: A python project for interpreting molecular dynamics trajectory metastable state classifications from machine-learning models
Author-email: shams mehdi <shamsmehdi222@gmail.com>
License: MIT License
Project-URL: Homepage, https://github.com/shams-mehdi/MDTerp
Keywords: MDTerp
Classifier: Intended Audience :: Developers
Classifier: License :: OSI Approved :: MIT License
Classifier: Natural Language :: English
Classifier: Programming Language :: Python :: 3.8
Classifier: Programming Language :: Python :: 3.9
Classifier: Programming Language :: Python :: 3.10
Classifier: Programming Language :: Python :: 3.11
Classifier: Programming Language :: Python :: 3.12
Requires-Python: >=3.8
License-File: LICENSE
Requires-Dist: numpy
Requires-Dist: scikit-learn
Requires-Dist: scipy
Requires-Dist: matplotlib
Provides-Extra: all
Requires-Dist: MDTerp[extra]; extra == "all"
Provides-Extra: extra
Requires-Dist: pandas; extra == "extra"
Dynamic: license-file
